webterm/__init__.py
webterm/logger.py
webterm/api/__init__.py
webterm/api/app.py
webterm/api/auth.py
webterm/api/websocket.py
webterm/api/routes/__init__.py
webterm/api/routes/auth.py
webterm/api/routes/files.py
webterm/api/routes/health.py
webterm/api/routes/terminal.py
webterm/cli/__init__.py
webterm/cli/webterm.py
webterm/core/__init__.py
webterm/core/config.py
webterm/core/pty_manager.py
webterm/core/session.py
webterm/core/stats.py
webterm/static/css/terminal.css
webterm/static/js/terminal.js
webterm/templates/index.html
webterm-0.0.2.dist-info/licenses/LICENSE
webterm-0.0.2.dist-info/METADATA
webterm-0.0.2.dist-info/WHEEL
webterm-0.0.2.dist-info/entry_points.txt
webterm-0.0.2.dist-info/top_level.txt
webterm-0.0.2.dist-info/RECORD
