Metadata-Version: 2.4
Name: webterm
Version: 0.0.2
Summary: webterm: web based terminal
Author: Abhishek Thakur
License: Apache 2.0
Project-URL: Homepage, https://github.com/abhishekkrthakur/webterm
Requires-Python: >=3.11
License-File: LICENSE
Requires-Dist: pydantic>=2.12.5
Requires-Dist: pydantic-settings>=2.0.0
Requires-Dist: rich>=14.3.1
Requires-Dist: fastapi>=0.128.0
Requires-Dist: uvicorn[standard]>=0.34.0
Requires-Dist: jinja2>=3.1.0
Requires-Dist: python-multipart>=0.0.6
Provides-Extra: dev
Requires-Dist: black==26.1.0; extra == "dev"
Requires-Dist: isort==7.0.0; extra == "dev"
Requires-Dist: flake8==7.3.0; extra == "dev"
Requires-Dist: pytest>=9.0.2; extra == "dev"
Requires-Dist: pytest-cov>=7.0.0; extra == "dev"
Requires-Dist: pytest-asyncio>=0.24.0; extra == "dev"
Requires-Dist: httpx>=0.27.0; extra == "dev"
Dynamic: license-file
